Ejercicio_5/ejercicio5.v
module  ROM(entrada,salida);

input  [6:0] entrada;
output  [12:0] salida;
reg [12:0] salida;

always @(entrada)
begin
  case (entrada)
    7'b??????0 : salida <= 13'b1000000001000;
    7'b00001?1 : salida <= 13'b0100000001000;
    7'b00000?1 : salida <= 13'b1000000001000;
    7'b00011?1 : salida <= 13'b1000000001000;
    7'b00010?1 : salida <= 13'b0100000001000;
    7'b0010??1 : salida <= 13'b0001001000010;
    7'b0011??1 : salida <= 13'b1001001100000;
    7'b0100??1 : salida <= 13'b0011010000010;
    7'b0101??1 : salida <= 13'b0011010000100;
    7'b0110??1 : salida <= 13'b1011010100000;
    7'b0111??1 : salida <= 13'b1000000111000;
    7'b1000?11 : salida <= 13'b0100000001000;
    7'b1000?01 : salida <= 13'b1000000001000;
    7'b1001?11 : salida <= 13'b1000000001000;
    7'b1001?01 : salida <= 13'b0100000001000;
    7'b1010??1 : salida <= 13'b0011011000010;
    7'b1011??1 : salida <= 13'b1011011100000;
    7'b1100??1 : salida <= 13'b0100000001000;
    7'b1101??1 : salida <= 13'b0000000001001;
    7'b1110??1 : salida <= 13'b0011100000010;
    7'b1111??1 : salida <= 13'b1011100100000;
    default : salida =13'b0000000000000;

endcase
end



endmodule

Ejercicio_5/ejercicio5_tb.v
module ROM_tb();

reg [6:0] entrada;
wire [12:0] salida;

ROM r1(entrada, salida);

initial begin
   #1 $display(" ");
   $display(" ");
   $display("ROM con cases");
   $display("Entada  Salida");
   $display("_______|_____");
   $monitor(" %b    %b    ", entrada, salida);
   end

initial begin

 entrada =7'b1111110 ;

#10 entrada =7'b??????1 ;
#10 entrada =7'b??????1 ;
#10 entrada =7'b00011?1 ;
#10 entrada =7'b0001011 ;
#10 entrada =7'b0010??1 ;
#10 entrada =7'b0011??1 ;
#10 entrada =7'b0100??1 ;
#10 entrada =7'b0101??1 ;
#10 entrada =7'b0110??1 ;
#10 entrada =7'b0111??1 ;
#10 entrada =7'b1000?11 ;
#10 entrada =7'b1000?01 ;
#10 entrada =7'b1001?11 ;
#10 entrada =7'b1001?01 ;
#10 entrada =7'b1010??1 ;
#10 entrada =7'b1011??1 ;
#10 entrada =7'b1100??1 ;
#10 entrada =7'b1101??1 ;
#10 entrada =7'b1110??1 ;
#10 entrada =7'b1111??1 ;


 #10 $finish;
end


  initial begin
  $dumpfile("ejercicio5_tb.vcd");
    $dumpvars(0,ROM_tb);
  end


endmodule

Ejercicio_5/ejercicio5_tb.vcd
$date
	Sat Oct 31 09:51:54 2020
$end
$version
	Icarus Verilog
$end
$timescale
	1ps
$end
$scope module ROM_tb $end
$var wire 13 ! salida [12:0] $end
$var reg 7 " entrada [6:0] $end
$scope module r1 $end
$var wire 7 # entrada [6:0] $end
$var reg 13 $ salida [12:0] $end
$upscope $end
$upscope $end
$enddefinitions $end
#0
$dumpvars
b0 $
b1111110 #
b1111110 "
b0 !
$end
#10
bz1 "
bz1 #
#30
b1000000001000 !
b1000000001000 $
b11z1 "
b11z1 #
#40
b0 !
b0 $
b1011 "
b1011 #
#50
b1001000010 !
b1001000010 $
b10zz1 "
b10zz1 #
#60
b1001001100000 !
b1001001100000 $
b11zz1 "
b11zz1 #
#70
b11010000010 !
b11010000010 $
b100zz1 "
b100zz1 #
#80
b11010000100 !
b11010000100 $
b101zz1 "
b101zz1 #
#90
b1011010100000 !
b1011010100000 $
b110zz1 "
b110zz1 #
#100
b1000000111000 !
b1000000111000 $
b111zz1 "
b111zz1 #
#110
b100000001000 !
b100000001000 $
b1000z11 "
b1000z11 #
#120
b1000000001000 !
b1000000001000 $
b1000z01 "
b1000z01 #
#130
b1001z11 "
b1001z11 #
#140
b100000001000 !
b100000001000 $
b1001z01 "
b1001z01 #
#150
b11011000010 !
b11011000010 $
b1010zz1 "
b1010zz1 #
#160
b1011011100000 !
b1011011100000 $
b1011zz1 "
b1011zz1 #
#170
b100000001000 !
b100000001000 $
b1100zz1 "
b1100zz1 #
#180
b1001 !
b1001 $
b1101zz1 "
b1101zz1 #
#190
b11100000010 !
b11100000010 $
b1110zz1 "
b1110zz1 #
#200
b1011100100000 !
b1011100100000 $
b1111zz1 "
b1111zz1 #
