Ejercicio_5/ejercicio5.v
module  ROM(entrada,salida);

input  [6:0] entrada;
output  [12:0] salida;
reg [12:0] salida;

always @(entrada)
begin
  case (entrada)
    7'b??????0 : salida <= 13'b1000000001000;
    7'b00001?1 : salida <= 13'b0100000001000;
    7'b00000?1 : salida <= 13'b1000000001000;
    7'b00011?1 : salida <= 13'b1000000001000;
    7'b00010?1 : salida <= 13'b0100000001000;
    7'b0010??1 : salida <= 13'b0001001000010;
    7'b0011??1 : salida <= 13'b1001001100000;
    7'b0100??1 : salida <= 13'b0011010000010;
    7'b0101??1 : salida <= 13'b0011010000100;
    7'b0110??1 : salida <= 13'b1011010100000;
    7'b0111??1 : salida <= 13'b1000000111000;
    7'b1000?11 : salida <= 13'b0100000001000;
    7'b1000?01 : salida <= 13'b1000000001000;
    7'b1001?11 : salida <= 13'b1000000001000;
    7'b1001?01 : salida <= 13'b0100000001000;
    7'b1010??1 : salida <= 13'b0011011000010;
    7'b1011??1 : salida <= 13'b1011011100000;
    7'b1100??1 : salida <= 13'b0100000001000;
    7'b1101??1 : salida <= 13'b0000000001001;
    7'b1110??1 : salida <= 13'b0011100000010;
    7'b1111??1 : salida <= 13'b1011100100000;
    default : salida =13'b0000000000000;

endcase
end



endmodule

Ejercicio_5/ejercicio5_tb.v
module ROM_tb();

reg [6:0] entrada;
wire [12:0] salida;

ROM r1(entrada, salida);

initial begin
   #1 $display(" ");
   $display(" ");
   $display("ROM con cases");
   $display("Entada  Salida");
   $display("_______|_____");
   $monitor(" %b    %b    ", entrada, salida);
   end

initial begin

 entrada =7'b1111110 ;

#10 entrada =7'b0000111 ;
#10 entrada =7'b0000001 ;
#10 entrada =7'b0001111 ;
#10 entrada =7'b0001011 ;
#10 entrada =7'b0010111 ;
#10 entrada =7'b0011001 ;
#10 entrada =7'b0100101 ;
#10 entrada =7'b0101111 ;
#10 entrada =7'b0110001 ;
#10 entrada =7'b0111111 ;
#10 entrada =7'b1000111 ;
#10 entrada =7'b1000101 ;
#10 entrada =7'b1001011 ;
#10 entrada =7'b1001101 ;
#10 entrada =7'b1010101 ;
#10 entrada =7'b1011111 ;
#10 entrada =7'b1100011 ;
#10 entrada =7'b1101001 ;
#10 entrada =7'b1110111 ;
#10 entrada =7'b1111111 ;
#10 entrada =7'b0101010 ;
#10 entrada =7'b1000011 ;
#10 entrada =7'b1101111 ;
#10 entrada =7'b0001111 ;
#10 entrada =7'b1110111 ;
#10 entrada =7'b1100111 ;
#10 entrada =7'b1000000 ;
#10 entrada =7'b1001111 ;
#10 entrada =7'b0101110 ;
#10 entrada =7'b0000001 ;
#10 entrada =7'b0010000 ;


 #10 $finish;
end


  initial begin
   $dumpfile("ejercicio5_tb.vcd");
    $dumpvars(0,ROM_tb);
  end


endmodule

Ejercicio_5/ejercicio5_tb.vcd
$date
	Sat Oct 31 15:49:04 2020
$end
$version
	Icarus Verilog
$end
$timescale
	1ps
$end
$scope module ROM_tb $end
$var wire 13 ! salida [12:0] $end
$var reg 7 " entrada [6:0] $end
$scope module r1 $end
$var wire 7 # entrada [6:0] $end
$var reg 13 $ salida [12:0] $end
$upscope $end
$upscope $end
$enddefinitions $end
#0
$dumpvars
b1000000001000 $
b1111110 #
b1111110 "
b1000000001000 !
$end
#10
b100000001000 !
b100000001000 $
b111 "
b111 #
#20
b1000000001000 !
b1000000001000 $
b1 "
b1 #
#30
b1111 "
b1111 #
#40
b100000001000 !
b100000001000 $
b1011 "
b1011 #
#50
b1001000010 !
b1001000010 $
b10111 "
b10111 #
#60
b1001001100000 !
b1001001100000 $
b11001 "
b11001 #
#70
b11010000010 !
b11010000010 $
b100101 "
b100101 #
#80
b11010000100 !
b11010000100 $
b101111 "
b101111 #
#90
b1011010100000 !
b1011010100000 $
b110001 "
b110001 #
#100
b1000000111000 !
b1000000111000 $
b111111 "
b111111 #
#110
b100000001000 !
b100000001000 $
b1000111 "
b1000111 #
#120
b1000000001000 !
b1000000001000 $
b1000101 "
b1000101 #
#130
b1001011 "
b1001011 #
#140
b100000001000 !
b100000001000 $
b1001101 "
b1001101 #
#150
b11011000010 !
b11011000010 $
b1010101 "
b1010101 #
#160
b1011011100000 !
b1011011100000 $
b1011111 "
b1011111 #
#170
b100000001000 !
b100000001000 $
b1100011 "
b1100011 #
#180
b1001 !
b1001 $
b1101001 "
b1101001 #
#190
b11100000010 !
b11100000010 $
b1110111 "
b1110111 #
#200
b1011100100000 !
b1011100100000 $
b1111111 "
b1111111 #
#210
b1000000001000 !
b1000000001000 $
b101010 "
b101010 #
#220
b100000001000 !
b100000001000 $
b1000011 "
b1000011 #
#230
b1001 !
b1001 $
b1101111 "
b1101111 #
#240
b1000000001000 !
b1000000001000 $
b1111 "
b1111 #
#250
b11100000010 !
b11100000010 $
b1110111 "
b1110111 #
#260
b100000001000 !
b100000001000 $
b1100111 "
b1100111 #
#270
b1000000001000 !
b1000000001000 $
b1000000 "
b1000000 #
#280
b1001111 "
b1001111 #
#290
b101110 "
b101110 #
#300
b1 "
b1 #
#310
b10000 "
b10000 #
