Ejercicio_1/Ejercicio_1.v
module flipflopD(clk,reset,enable,D,Q);

input wire clk;
input wire reset;
input wire enable;
input wire D;
output reg Q;


always @(posedge clk , posedge reset)

begin:flipflopD1bit
 if (clk) begin
  if (reset)  begin
    Q<= 1'b0;
  end
  else if(enable) begin
  Q <= D;
  end
  end
end
endmodule

module flipflopD2(clk,reset,enable,D,Q);

input wire clk;
input wire reset;
input wire enable;
input wire [1:0] D;
output reg [1:0] Q;


always @(posedge clk , posedge reset)

begin:flipflopD2bit
 if (clk) begin
  if (reset)  begin
    Q<= 2'b00;
  end
  else if(enable) begin
  Q <= D;
  end
  end
end
endmodule

module flipflopD4(clk,reset,enable,D,Q);

input wire clk;
input wire reset;
input wire enable;
input wire [3:0] D;
output reg [3:0] Q;


always @(posedge clk , posedge reset)

begin:flipflopD4bit
 if (clk) begin
  if (reset)  begin
    Q<= 4'b0000;
  end
  else if(enable) begin
  Q <= D;
  end
  end
end


endmodule

Ejercicio_1/Ejercicio_1_tb.v
module flipflopD_tb();


reg clk, reset, enable, D;
wire Q;

reg clk1, reset1, enable1;
reg [1:0] D1;
wire [1:0] Q1;

reg clk2, reset2, enable2;
reg [3:0] D2;
wire [3:0] Q2;


flipflopD f1(clk,reset,enable,D,Q);
flipflopD2 f2(clk1,reset1,enable1,D1,Q1);
flipflopD4 f4(clk2,reset2,enable2,D2,Q2);

initial begin
   #1 $display(" ");
   $display(" ");
   $display("flipflop tipo D 1 bit");
   $display("clk Reset Enable  D Q");
   $display("________________|_____");
   $monitor(" %b    %b     %b      %b %b  ", clk, reset, enable ,D ,Q);
   end

   always
   #1 clk = ~clk;

   initial begin
 clk = 0;
 enable = 1;
 reset= 1;
 D = 1;

    /////////////////////
  #1 enable = 1;
  #1 reset = 1;
  #1 D = 0;
    /////////////////////
  #1   enable = 1;
  #1   reset = 0;
  #1 D = 1;
    ///////////////////
  #1 enable = 1;
  #1 reset = 0;
  #1   D = 0;




  end

  initial begin
     #10 $display(" ");
     $display(" ");
     $display("flipflop tipo D 2 bits");
     $display("clk Reset Enable  D   Q");
     $display("________________|_____");
     $monitor(" %b    %b     %b      %b %b  ", clk1, reset1, enable1 ,D1 ,Q1);
     end

     always
     #10 clk1 = ~clk1;

     initial begin
     clk1 = 0;
     enable1 = 0;
     reset1= 1;
     D1 = 2'b00;
      /////////////////////
    #10 enable1 = 1;
    #10reset1 = 1;
    #10 D1 = 2'b01;
      /////////////////////
    #10  enable1 = 1;
    #10  reset1 = 0;
    #10 D1 = 2'b10;
      ///////////////////
    #10 enable1 = 1;
    #10 reset1 = 0;
    #10 D1 = 2'b00;
    /////////////////////
    #10   enable1 = 1;
    #10   reset1 = 0;
    #10  D1 = 2'b11;
    /////////////////////
    #10 enable1 = 1;
    #10   reset1 = 0;
    #10 D1 = 2'b10;
    /////////////////////
    #10   enable1 = 1;
    #10   reset1 = 0;
    #10 D1 = 2'b00;
    /////////////////////
    #10   enable1 = 1;
    #10   reset1 = 1;
    #10  D1 = 2'b11;

    end




    initial begin
       #200 $display(" ");
       $display(" ");
       $display("flipflop tipo D 4 bits");
       $display("clk Reset Enable  D      Q");
       $display("________________|___________");
       $monitor(" %b    %b     %b      %b %b  ", clk2, reset2, enable2 ,D2 ,Q2);
       end

       always
       #20 clk2 = ~clk2;

       initial begin
       clk2 = 0;
       enable2 = 0;
       reset2= 1;
       D2 = 2'b0000;
        /////////////////////
      #20 enable2 = 1;
      #20 reset2 = 1;
      #20 D2 = 2'b0001;
        /////////////////////
      #20 enable2 = 1;
      #20 reset2 = 0;
      #20 D2 = 2'b1001;
        ///////////////////
      #20 enable2 = 1;
      #20 reset2 = 0;
      #20 D2 = 2'b0111;
      /////////////////////
      #20  enable2 = 1;
      #20  reset2 = 0;
      #20  D2 = 2'b1111;
      /////////////////////
      #20 enable2 = 1;
      #20  reset2 = 0;
      #20 D2 = 2'b1000;
      /////////////////////
      #20  enable2 = 1;
      #20  reset2 = 0;
      #20 D2 = 2'b010;
      /////////////////////
      #20  enable2 = 1;
      #20  reset2 = 1;
      #20  D2 = 2'b000;



      #1 $finish;

      end


  initial begin
   $dumpfile("Ejercicio_1_tb.vcd");
    $dumpvars(0,flipflopD_tb);
  end

endmodule

Ejercicio_1/Ejercicio_1_tb.vcd
$date
	Sat Oct 31 04:58:52 2020
$end
$version
	Icarus Verilog
$end
$timescale
	1ps
$end
$scope module flipflopD_tb $end
$var wire 4 ! Q2 [3:0] $end
$var wire 2 " Q1 [1:0] $end
$var wire 1 # Q $end
$var reg 1 $ D $end
$var reg 2 % D1 [1:0] $end
$var reg 4 & D2 [3:0] $end
$var reg 1 ' clk $end
$var reg 1 ( clk1 $end
$var reg 1 ) clk2 $end
$var reg 1 * enable $end
$var reg 1 + enable1 $end
$var reg 1 , enable2 $end
$var reg 1 - reset $end
$var reg 1 . reset1 $end
$var reg 1 / reset2 $end
$scope module f1 $end
$var wire 1 $ D $end
$var wire 1 ' clk $end
$var wire 1 * enable $end
$var wire 1 - reset $end
$var reg 1 # Q $end
$scope begin flipflopD1bit $end
$upscope $end
$upscope $end
$scope module f2 $end
$var wire 2 0 D [1:0] $end
$var wire 1 ( clk $end
$var wire 1 + enable $end
$var wire 1 . reset $end
$var reg 2 1 Q [1:0] $end
$scope begin flipflopD2bit $end
$upscope $end
$upscope $end
$scope module f4 $end
$var wire 4 2 D [3:0] $end
$var wire 1 ) clk $end
$var wire 1 , enable $end
$var wire 1 / reset $end
$var reg 4 3 Q [3:0] $end
$scope begin flipflopD4bit $end
$upscope $end
$upscope $end
$upscope $end
$enddefinitions $end
#0
$dumpvars
bx 3
b0 2
bx 1
b0 0
1/
1.
1-
0,
0+
1*
0)
0(
0'
b0 &
b0 %
1$
x#
bx "
bx !
$end
#1
0#
1'
#2
0'
#3
0$
1'
#4
0'
#5
0-
1'
#6
1$
0'
#7
1#
1'
#8
0'
#9
0#
0$
1'
#10
b0 "
b0 1
0'
1+
1(
#11
1'
#12
0'
#13
1'
#14
0'
#15
1'
#16
0'
#17
1'
#18
0'
#19
1'
#20
b0 !
b0 3
0'
0(
1,
1)
#21
1'
#22
0'
#23
1'
#24
0'
#25
1'
#26
0'
#27
1'
#28
0'
#29
1'
#30
0'
b1 %
b1 0
1(
#31
1'
#32
0'
#33
1'
#34
0'
#35
1'
#36
0'
#37
1'
#38
0'
#39
1'
#40
0'
0(
0)
#41
1'
#42
0'
#43
1'
#44
0'
#45
1'
#46
0'
#47
1'
#48
0'
#49
1'
#50
b1 "
b1 1
0'
0.
1(
#51
1'
#52
0'
#53
1'
#54
0'
#55
1'
#56
0'
#57
1'
#58
0'
#59
1'
#60
0'
b10 %
b10 0
0(
b1 &
b1 2
1)
#61
1'
#62
0'
#63
1'
#64
0'
#65
1'
#66
0'
#67
1'
#68
0'
#69
1'
#70
b10 "
b10 1
0'
1(
#71
1'
#72
0'
#73
1'
#74
0'
#75
1'
#76
0'
#77
1'
#78
0'
#79
1'
#80
0'
0(
0)
#81
1'
#82
0'
#83
1'
#84
0'
#85
1'
#86
0'
#87
1'
#88
0'
#89
1'
#90
b0 "
b0 1
0'
b0 %
b0 0
1(
#91
1'
#92
0'
#93
1'
#94
0'
#95
1'
#96
0'
#97
1'
#98
0'
#99
1'
#100
b1 !
b1 3
0'
0(
0/
1)
#101
1'
#102
0'
#103
1'
#104
0'
#105
1'
#106
0'
#107
1'
#108
0'
#109
1'
#110
0'
1(
#111
1'
#112
0'
#113
1'
#114
0'
#115
1'
#116
0'
#117
1'
#118
0'
#119
1'
#120
0'
b11 %
b11 0
0(
0)
#121
1'
#122
0'
#123
1'
#124
0'
#125
1'
#126
0'
#127
1'
#128
0'
#129
1'
#130
b11 "
b11 1
0'
1(
#131
1'
#132
0'
#133
1'
#134
0'
#135
1'
#136
0'
#137
1'
#138
0'
#139
1'
#140
0'
0(
1)
#141
1'
#142
0'
#143
1'
#144
0'
#145
1'
#146
0'
#147
1'
#148
0'
#149
1'
#150
b10 "
b10 1
0'
b10 %
b10 0
1(
#151
1'
#152
0'
#153
1'
#154
0'
#155
1'
#156
0'
#157
1'
#158
0'
#159
1'
#160
0'
0(
0)
#161
1'
#162
0'
#163
1'
#164
0'
#165
1'
#166
0'
#167
1'
#168
0'
#169
1'
#170
0'
1(
#171
1'
#172
0'
#173
1'
#174
0'
#175
1'
#176
0'
#177
1'
#178
0'
#179
1'
#180
b11 !
b11 3
0'
b0 %
b0 0
0(
b11 &
b11 2
1)
#181
1'
#182
0'
#183
1'
#184
0'
#185
1'
#186
0'
#187
1'
#188
0'
#189
1'
#190
b0 "
b0 1
0'
1(
#191
1'
#192
0'
#193
1'
#194
0'
#195
1'
#196
0'
#197
1'
#198
0'
#199
1'
#200
0'
1.
0(
0)
#201
1'
#202
0'
#203
1'
#204
0'
#205
1'
#206
0'
#207
1'
#208
0'
#209
1'
#210
0'
b11 %
b11 0
1(
