Ejercicio_3/Ejercicio_3.v
module FFD(input wire clk, reset, enable, D, output reg Q);

  always @(posedge clk or posedge reset or posedge enable)
    begin

      if (reset) Q <= 1'b0;
      else if (enable) Q <= D;
      else Q <= Q;
    end

endmodule



module flipflopjk(input wire clk,reset,enable,j,k, output wire Q);

FFD f1(clk,reset,enable,D,Q);

wire NOT1;
wire NOT2;
wire AND1;
wire AND2;

not not1(NOT1,k);
not not2(NOT2,Q);
and and1(AND1,NOT1,j);
and and2(AND2,NOT2,Q);
or or1(D,AND1,AND2);


endmodule

Ejercicio_3/Ejercicio_3_tb.v
module Ejercicio_3_tb();


reg clk, reset, enable;
reg j,k;
wire q;

flipflopjk f1(clk,reset,enable,j,k,q);

initial begin
   #10 $display(" ");
   $display(" ");
   $display("flipflop tipo jk");
   $display("clk Reset Enable J K | Q");
   $display("_____________________");
   $monitor(" %b    %b      %b    %b %b | %b  ", clk, reset, enable ,k ,j, q);
   end

   always
   #10 clk = ~clk;

   initial begin
 clk = 0;
 enable = 1;
 reset= 1;

 j=0;
 k=0;

 ///////////////////////

 #10
 reset=1;
 enable=1;
 reset=0;
 j=0;
 k=0;

 #10
 reset=1;
 enable=1;
 reset=0;
 j=1;
 k=0;
 /////////////
 #10
 reset=1;
 enable=1;
 reset=0;
 j=0;
 k=1;

#10
 /////////////

 reset=1;
 enable=1;
 reset=0;
 j=1;
 k=1;
 #10

 reset=1;
 enable=1;
 reset=0;
 j=0;
 k=0;
 /////////////
 #10
 reset=1;
 enable=1;
 reset=0;
 j=1;
 k=0;
 #10



 reset=1;
 enable=1;
 reset=0;
 j=1;
 k=1;
#10
reset=1;

  #10 $finish;

  end


  initial begin
    $dumpfile("Ejercicio_3_tb.vcd");
    $dumpvars(0,Ejercicio_3_tb);
  end

endmodule

Ejercicio_3/Ejercicio_3_tb.vcd
$date
	Sat Oct 31 04:47:50 2020
$end
$version
	Icarus Verilog
$end
$timescale
	1ps
$end
$scope module Ejercicio_3_tb $end
$var wire 1 ! q $end
$var reg 1 " clk $end
$var reg 1 # enable $end
$var reg 1 $ j $end
$var reg 1 % k $end
$var reg 1 & reset $end
$scope module f1 $end
$var wire 1 ' AND1 $end
$var wire 1 ( AND2 $end
$var wire 1 ) D $end
$var wire 1 * NOT1 $end
$var wire 1 + NOT2 $end
$var wire 1 " clk $end
$var wire 1 # enable $end
$var wire 1 $ j $end
$var wire 1 % k $end
$var wire 1 & reset $end
$var wire 1 ! Q $end
$scope module f1 $end
$var wire 1 ) D $end
$var wire 1 " clk $end
$var wire 1 # enable $end
$var wire 1 & reset $end
$var reg 1 ! Q $end
$upscope $end
$upscope $end
$upscope $end
$enddefinitions $end
#0
$dumpvars
1+
1*
0)
0(
0'
1&
0%
0$
1#
0"
0!
$end
#10
0&
1"
#20
1)
1'
1$
0&
0"
#30
0+
1!
0)
0*
0'
1%
0$
0&
1"
#40
1+
0!
1$
0&
0"
#50
1*
0%
0$
0&
1"
#60
1)
1'
1$
0&
0"
#70
0+
1!
0)
0'
0*
1%
0&
1"
#80
1+
0!
1&
0"
